examples/__init__.py
examples/cdx2spdx.py
examples/cdxconvert_1.5.py
examples/check_synoyms.py
examples/conversion.py
examples/converter.py
examples/create.py
examples/create_annotation.py
examples/create_mlbom.py
examples/create_services.py
examples/create_system.py
examples/exception.py
examples/fast_validate.py
examples/intoto.py
examples/mlbom_summary.py
examples/openchain.py
examples/parse.py
examples/parse2.py
examples/purl_parser.py
examples/regenerate.py
examples/spdx2cdx.py
examples/summary.py
examples/supplier.py
examples/test.py
examples/test2.py
examples/validate.py
examples/vuln_summary.py
lib4sbom/__init__.py
lib4sbom/exception.py
lib4sbom/generator.py
lib4sbom/license.py
lib4sbom/output.py
lib4sbom/parser.py
lib4sbom/sbom.py
lib4sbom/validator.py
lib4sbom/version.py
lib4sbom/cyclonedx/__init__.py
lib4sbom/cyclonedx/cyclonedx_generator.py
lib4sbom/cyclonedx/cyclonedx_parser.py
lib4sbom/cyclonedx/cyclonedx_validator.py
lib4sbom/data/__init__.py
lib4sbom/data/annotation.py
lib4sbom/data/composition.py
lib4sbom/data/document.py
lib4sbom/data/file.py
lib4sbom/data/license.py
lib4sbom/data/modelcard.py
lib4sbom/data/package.py
lib4sbom/data/relationship.py
lib4sbom/data/service.py
lib4sbom/data/vulnerability.py
lib4sbom/license_data/license_synonyms.txt
lib4sbom/license_data/license_type.txt
lib4sbom/license_data/spdx_licenses.json
lib4sbom/license_data/text/0bsd.html
lib4sbom/license_data/text/389-exception.html
lib4sbom/license_data/text/3d-slicer-1.0.html
lib4sbom/license_data/text/aal.html
lib4sbom/license_data/text/abstyles.html
lib4sbom/license_data/text/adacore-doc.html
lib4sbom/license_data/text/adobe-2006.html
lib4sbom/license_data/text/adobe-display-postscript.html
lib4sbom/license_data/text/adobe-glyph.html
lib4sbom/license_data/text/adobe-utopia.html
lib4sbom/license_data/text/adsl.html
lib4sbom/license_data/text/afl-1.1.html
lib4sbom/license_data/text/afl-1.2.html
lib4sbom/license_data/text/afl-2.0.html
lib4sbom/license_data/text/afl-2.1.html
lib4sbom-0.9.2.dist-info/LICENSE
lib4sbom-0.9.2.dist-info/METADATA
lib4sbom-0.9.2.dist-info/WHEEL
lib4sbom-0.9.2.dist-info/top_level.txt
lib4sbom-0.9.2.dist-info/RECORD
